karrio/mappers/australiapost/__init__.py
karrio/mappers/australiapost/mapper.py
karrio/mappers/australiapost/proxy.py
karrio/mappers/australiapost/settings.py
karrio/plugins/australiapost/__init__.py
karrio/providers/australiapost/__init__.py
karrio/providers/australiapost/error.py
karrio/providers/australiapost/manifest.py
karrio/providers/australiapost/rate.py
karrio/providers/australiapost/tracking.py
karrio/providers/australiapost/units.py
karrio/providers/australiapost/utils.py
karrio/providers/australiapost/shipment/__init__.py
karrio/providers/australiapost/shipment/cancel.py
karrio/providers/australiapost/shipment/create.py
karrio/schemas/australiapost/__init__.py
karrio/schemas/australiapost/error_response.py
karrio/schemas/australiapost/label_request.py
karrio/schemas/australiapost/label_response.py
karrio/schemas/australiapost/manifest_request.py
karrio/schemas/australiapost/manifest_response.py
karrio/schemas/australiapost/rate_request.py
karrio/schemas/australiapost/rate_response.py
karrio/schemas/australiapost/shipment_request.py
karrio/schemas/australiapost/shipment_response.py
karrio/schemas/australiapost/tracking_request.py
karrio/schemas/australiapost/tracking_response.py
karrio_australiapost-2026.1.4.dist-info/METADATA
karrio_australiapost-2026.1.4.dist-info/WHEEL
karrio_australiapost-2026.1.4.dist-info/entry_points.txt
karrio_australiapost-2026.1.4.dist-info/top_level.txt
karrio_australiapost-2026.1.4.dist-info/RECORD
